iterlab/__init__.py
iterlab/iterlab.py
iterlab-0.1.4.dist-info/LICENSE
iterlab-0.1.4.dist-info/METADATA
iterlab-0.1.4.dist-info/WHEEL
iterlab-0.1.4.dist-info/RECORD
